phylovega/__init__.py
phylovega/__version__.py
phylovega/_core.py
phylovega/_schema.py
phylovega/app.py
phylovega/chart.py
phylovega/data.py
phylovega/marks.py
phylovega/signals.py
phylovega/traitlets.py
phylovega-0.3.dist-info/METADATA
phylovega-0.3.dist-info/WHEEL
phylovega-0.3.dist-info/entry_points.txt
phylovega-0.3.dist-info/top_level.txt
phylovega-0.3.dist-info/RECORD
