Metadata-Version: 2.1
Name: phylovega
Version: 0.3
Summary: Interactive Phylogenetic trees in Vega from Python.
Home-page: https://github.com/Zsailer/phylovega
Author: Zach Sailer
Author-email: zachsailer@gmail.com
License: MIT
Platform: UNKNOWN
Classifier: License :: OSI Approved :: MIT License
Classifier: Programming Language :: Python
Classifier: Programming Language :: Python :: 3
Classifier: Programming Language :: Python :: 3.6
Classifier: Programming Language :: Python :: Implementation :: CPython
Classifier: Programming Language :: Python :: Implementation :: PyPy
Requires-Python: >=3.4.0
Requires-Dist: phylopandas
Requires-Dist: vega
